vihi_nova_act/__init__.py
vihi_nova_act/__version__.py
vihi_nova_act/nova_act.py
vihi_nova_act/py.typed
vihi_nova_act/artifacts/chrome-mv3-prod/actuationHelpers.18250396.js
vihi_nova_act/artifacts/chrome-mv3-prod/content.d585fe88.js
vihi_nova_act/artifacts/chrome-mv3-prod/icon128.plasmo.1b077857.png
vihi_nova_act/artifacts/chrome-mv3-prod/icon16.plasmo.ef6030e0.png
vihi_nova_act/artifacts/chrome-mv3-prod/icon32.plasmo.598c4db3.png
vihi_nova_act/artifacts/chrome-mv3-prod/icon48.plasmo.0ee1303b.png
vihi_nova_act/artifacts/chrome-mv3-prod/icon64.plasmo.8d03a7fe.png
vihi_nova_act/artifacts/chrome-mv3-prod/mainWorldActuationHelper.d216d441.js
vihi_nova_act/artifacts/chrome-mv3-prod/manifest.json
vihi_nova_act/artifacts/chrome-mv3-prod/static/background/index.js
vihi_nova_act/impl/__init__.py
vihi_nova_act/impl/backend.py
vihi_nova_act/impl/common.py
vihi_nova_act/impl/dispatcher.py
vihi_nova_act/impl/dispatcher_factory.py
vihi_nova_act/impl/extension.py
vihi_nova_act/impl/inputs.py
vihi_nova_act/impl/keyboard_event_watcher.py
vihi_nova_act/impl/message_encrypter.py
vihi_nova_act/impl/playwright.py
vihi_nova_act/impl/playwright_instance_options.py
vihi_nova_act/impl/protocol.py
vihi_nova_act/impl/run_info_compiler.py
vihi_nova_act/impl/telemetry.py
vihi_nova_act/impl/window_messages.py
vihi_nova_act/impl/custom_actuation/custom_dispatcher.py
vihi_nova_act/impl/custom_actuation/interface/actuator.py
vihi_nova_act/impl/custom_actuation/interface/browser.py
vihi_nova_act/impl/custom_actuation/interface/playwright_pages.py
vihi_nova_act/impl/custom_actuation/interface/types/agent_redirect_error.py
vihi_nova_act/impl/custom_actuation/interface/types/bbox_dict.py
vihi_nova_act/impl/custom_actuation/interface/types/click_options.py
vihi_nova_act/impl/custom_actuation/interface/types/dimensions_dict.py
vihi_nova_act/impl/custom_actuation/interface/types/element_dict.py
vihi_nova_act/impl/custom_actuation/interface/types/program_error_response.py
vihi_nova_act-2.0.78.1.dist-info/licenses/LICENSE
vihi_nova_act-2.0.78.1.dist-info/licenses/NOTICE
vihi_nova_act-2.0.78.1.dist-info/METADATA
vihi_nova_act-2.0.78.1.dist-info/WHEEL
vihi_nova_act-2.0.78.1.dist-info/top_level.txt
vihi_nova_act-2.0.78.1.dist-info/RECORD
