Metadata-Version: 2.4
Name: vihi-nova-act
Version: 2.0.78.1
Summary: A Python SDK for Amazon Nova Act.
Author-email: Amazon Nova Act <nova-act@amazon.com>, Tharoosha Vihidun <tharooshavihidun@gmail.com>
License-Expression: Apache-2.0
Requires-Python: >=3.10
License-File: LICENSE
License-File: NOTICE
Requires-Dist: cryptography
Requires-Dist: fire
Requires-Dist: install_playwright
Requires-Dist: jsonschema
Requires-Dist: numpy<=2.2.6
Requires-Dist: pandas
Requires-Dist: pillow
Requires-Dist: playwright==1.54.0
Requires-Dist: pydantic>=2.10.6
Requires-Dist: requests
Requires-Dist: retry
Requires-Dist: pytz
Requires-Dist: strands-agents>=0.1.9
Requires-Dist: strands-agents-tools
Provides-Extra: dev
Requires-Dist: build; extra == "dev"
Requires-Dist: setuptools; extra == "dev"
Requires-Dist: twine; extra == "dev"
Requires-Dist: wheel; extra == "dev"
Dynamic: license-file
